pytrs/__init__.py
pytrs/trs.py
HeyTranserSDK-0.1.dist-info/LICENSE
HeyTranserSDK-0.1.dist-info/METADATA
HeyTranserSDK-0.1.dist-info/WHEEL
HeyTranserSDK-0.1.dist-info/top_level.txt
HeyTranserSDK-0.1.dist-info/RECORD
