Metadata-Version: 2.1
Name: HeyTranserSDK
Version: 0.1
Summary: HeyTranser Python SDK
Home-page: https://github.com/HeyTranser/PythonSDK
Author: Maicarons
Author-email: maicarons@outlook.com
License: Apache License, Version 2.0
Project-URL: Bug Tracker, https://github.com/HeyTranser/PythonSDK/issues
Platform: UNKNOWN
Classifier: Programming Language :: Python :: 3
Classifier: License :: OSI Approved :: Apache Software License
Classifier: Operating System :: OS Independent
Requires-Python: >=3
Requires-Dist: pyyaml
